python_webflow_exporter-1.0.6.dist-info/licenses/LICENSE.md
webexp/__init__.py
webexp/cli.py
python_webflow_exporter-1.0.6.dist-info/METADATA
python_webflow_exporter-1.0.6.dist-info/WHEEL
python_webflow_exporter-1.0.6.dist-info/entry_points.txt
python_webflow_exporter-1.0.6.dist-info/top_level.txt
python_webflow_exporter-1.0.6.dist-info/RECORD
