Metadata-Version: 2.4
Name: python-webflow-exporter
Version: 1.0.6
Summary: A CLI tool to export Webflow pages
Author-email: Simon Kobler <github@kobler.me>
License: MIT
Requires-Python: >=3.10
License-File: LICENSE.md
Requires-Dist: requests==2.32.4
Requires-Dist: argparse==1.4.0
Requires-Dist: beautifulsoup4==4.13.4
Requires-Dist: halo==0.0.31
Requires-Dist: pylint==3.3.7
Requires-Dist: setuptools==80.9.0
Dynamic: license-file
